predict_phytolrr.py
phytolrr_predictor/__init__.py
phytolrr_predictor/resources/__init__.py
phytolrr_predictor/resources/results.html
phytolrr_predictor/tools/__init__.py
phytolrr_predictor/tools/exception.py
phytolrr_predictor/tools/motifs.py
phytolrr_predictor/tools/pssm_matrix.py
predict_phytolrr-1.0.2.dist-info/LICENSE
predict_phytolrr-1.0.2.dist-info/METADATA
predict_phytolrr-1.0.2.dist-info/WHEEL
predict_phytolrr-1.0.2.dist-info/entry_points.txt
predict_phytolrr-1.0.2.dist-info/top_level.txt
predict_phytolrr-1.0.2.dist-info/RECORD
