Metadata-Version: 2.1
Name: predict-phytolrr
Version: 1.0.2
Summary: A tool which predict phyto-LRRs from a sequences.
Home-page: https://github.com/phytolrr/predict-phytolrr
Author: PhytoLRR
Author-email: phytolrr@163.com
License: UNKNOWN
Platform: UNKNOWN
Classifier: License :: OSI Approved :: GNU General Public License v3 (GPLv3)
Classifier: Development Status :: 4 - Beta
Classifier: Operating System :: OS Independent
Classifier: Programming Language :: Python :: 3
Requires-Python: >=3.6
Requires-Dist: biopython (<1.78,>=1.73)
Requires-Dist: numpy (>=1.16.3)
